license.md
matmap/__init__.py
matmap/base.py
matmap/qast_utils/loopReader.py
matmap/transforms/ReorderingTransform.py
matmap/transforms/TilingTransform.py
matmap/tuning/gptune_harness.py
matmap/tuning/tunableTransform
matmap-0.1.0.dist-info/WHEEL
matmap-0.1.0.dist-info/METADATA
matmap-0.1.0.dist-info/RECORD
