Metadata-Version: 2.1
Name: matmap
Version: 0.1.0
Summary: MatMap: A Modular, Automatable, Tunable Mapper for Accelerator Programming
Home-page: https://github.com/gdinh/matmap
License: Apache-2.0
Keywords: scheduling,language,performance,dsl,autotuning
Author: Grace Dinh
Author-email: dinh@berkeley.edu
Maintainer: Grace Dinh
Maintainer-email: dinh@berkeley.edu
Requires-Python: >=3.9,<4.0
Classifier: Development Status :: 2 - Pre-Alpha
Classifier: Intended Audience :: Developers
Classifier: Intended Audience :: Science/Research
Classifier: License :: OSI Approved :: Apache Software License
Classifier: Operating System :: OS Independent
Classifier: Programming Language :: Python :: 3
Classifier: Programming Language :: Python :: 3.10
Classifier: Programming Language :: Python :: 3.9
Classifier: Topic :: Scientific/Engineering
Classifier: Topic :: Scientific/Engineering :: Artificial Intelligence
Classifier: Topic :: Scientific/Engineering :: Electronic Design Automation (EDA)
Classifier: Topic :: Scientific/Engineering :: Image Processing
Classifier: Topic :: Software Development
Classifier: Topic :: Software Development :: Code Generators
Classifier: Topic :: Software Development :: Compilers
Requires-Dist: cvxpy (>=1.0.0,<2.0.0)
Requires-Dist: exo-lang (>=0.0.2,<0.0.3)
Project-URL: Repository, https://github.com/gdinh/matmap
